gitlab_lint/__init__.py
gitlab_lint/gll.py
gitlab_lint_srt-0.8.1.dist-info/LICENSE.txt
gitlab_lint_srt-0.8.1.dist-info/METADATA
gitlab_lint_srt-0.8.1.dist-info/WHEEL
gitlab_lint_srt-0.8.1.dist-info/entry_points.txt
gitlab_lint_srt-0.8.1.dist-info/RECORD
