Metadata-Version: 2.1
Name: gitlab-lint-srt
Version: 0.8.1
Summary: This is a CLI application to quickly lint .gitlab-ci.yml files using the gitlab api
Home-page: https://github.com/elijah-roberts/gitlab-lint
License: MIT
Keywords: gitlab,lint
Author: Elijah Roberts
Author-email: elijah@elijahjamesroberts.com
Requires-Python: >=3.10,<4.0
Classifier: Environment :: Console
Classifier: License :: OSI Approved :: MIT License
Classifier: Operating System :: OS Independent
Classifier: Programming Language :: Python :: 3
Classifier: Programming Language :: Python :: 3.10
Classifier: Programming Language :: Python :: 3.11
Classifier: Programming Language :: Python :: 3.12
Classifier: Topic :: Software Development :: Quality Assurance
Requires-Dist: click (>=8.1.3,<9.0.0)
Requires-Dist: fqdn (>=1.5.1,<2.0.0)
Requires-Dist: requests (>=2.31.0,<3.0.0)
Project-URL: Repository, https://github.com/elijah-roberts/gitlab-lint
